{
  "language": "EN",
  "summary": "",
  "track": {
    "title": "Mind the Geek",
    "id": "2758"
  },
  "room": {
    "id": "4707",
    "title": "Room 7"
  },
  "title": "Math Behind Software",
  "format": {
    "id": "960",
    "title": "Quickie",
    "duration": "PT15m"
  },
  "description": "<p>Be aware: it's mostly theoretical math here!</p><p>But math is an essential part of our everyday work as software engineers, so it's worth having a closer look at what the math behind software is.</p><p>This presentation is focused on the concept of vacuous truth and how it can impact our work.</p><p>The talk opens with an intro on how and where math intersects with software development and moves on to defining vacuous truth exactly and a brief explanation of why calling .allMatch on empty Stream will always return true.</p>",
  "id": "1902",
  "speakers": [
    {
      "fullName": "Bartłomiej Żyliński",
      "photoUrl": "https://devoxxian-image-thumbnails.s3-eu-west-1.amazonaws.com/profile-88e555b7-d301-4361-bac4-3fb49f561392.jpg",
      "companyName": "SoftwareMill",
      "id": "1853"
    }
  ]
}